aws_spitzel/__init__.py
aws_spitzel/__main__.py
aws_spitzel/cli.py
victorykit_aws_spitzel-1.0.7.dist-info/LICENSE
victorykit_aws_spitzel-1.0.7.dist-info/METADATA
victorykit_aws_spitzel-1.0.7.dist-info/NOTICE.md
victorykit_aws_spitzel-1.0.7.dist-info/WHEEL
victorykit_aws_spitzel-1.0.7.dist-info/entry_points.txt
victorykit_aws_spitzel-1.0.7.dist-info/top_level.txt
victorykit_aws_spitzel-1.0.7.dist-info/zip-safe
victorykit_aws_spitzel-1.0.7.dist-info/RECORD
