Metadata-Version: 2.1
Name: victorykit-aws-spitzel
Version: 1.0.7
Summary: Advanced CloudTrail Event History Lookup for AWS IAM Forensics
Home-page: https://victorykit.bitbucket.io/py-aws-spitzel
Author: T. Rodney (victory-k.it)
Author-email: py-aws-spitzel@victoryk.it
Project-URL: Bug Tracker, https://bitbucket.org/victorykit/py-aws-spitzel/issues
Classifier: Development Status :: 4 - Beta
Classifier: Environment :: Other Environment
Classifier: Intended Audience :: Developers
Classifier: Topic :: Utilities
Classifier: Topic :: Security
Classifier: Programming Language :: Python :: 3.7
Classifier: Programming Language :: Python :: 3.8
Classifier: Programming Language :: Python :: 3.9
Classifier: Operating System :: OS Independent
Classifier: License :: Other/Proprietary License
Requires-Python: >=3.7
License-File: LICENSE
License-File: NOTICE.md
Requires-Dist: boto3 (<2,>=1.24.2)
Requires-Dist: jsonpath (<1,>=0.82)
